{
    "nid": "26285",
    "uuid": "e91ad0df-6d98-4869-a433-6ec8ab66afe0",
    "vid": "26285",
    "langcode": "fr",
    "type": [
        {
            "target_id": "radar"
        }
    ],
    "revisionTimestamp": "1681741044",
    "revisionUid": [
        {
            "target_id": "1"
        }
    ],
    "revisionLog": [],
    "status": "1",
    "uid": [
        {
            "target_id": "1"
        }
    ],
    "title": "I_30_003",
    "created": "1681741044",
    "changed": "1681741044",
    "promote": "0",
    "sticky": "0",
    "defaultLangcode": "1",
    "revisionTranslationAffected": "1",
    "path": [
        {
            "langcode": "fr"
        }
    ],
    "department": "30 - Gard",
    "itineraireEntree": [],
    "itineraireSortie": [],
    "radarDirection": [],
    "radarEquipment": "AXIMUM",
    "radarGeolocalisation": "POINT (5.049049 47.372605)",
    "radarInstallDate": "2017-10-05T16:17:24",
    "radarPlace": "-",
    "radarRoad": "D980, A9, D976, D6086, N86, D311, D865, D26, D609, D9, D6580, D177, D138, D121, D377, D680, D6, N580",
    "radarTronconKm": "37,3",
    "radarType": [
        {
            "tid": "19",
            "uuid": "6b6992f4-89c5-48e7-a623-8d9a0ce18836",
            "revisionId": "19",
            "langcode": "fr",
            "vid": [
                {
                    "target_id": "radar_types"
                }
            ],
            "revisionCreated": [],
            "revisionUser": [],
            "revisionLogMessage": [],
            "status": "1",
            "name": "Itin\u00e9raires",
            "description": "Sur toute la longueur de cet itin\u00e9raire, il peut y avoir de un \u00e0 plusieurs radars, de plusieurs types.\r\n<br>\r\n<br>\r\n<a href=\"http://www.securite-routiere.gouv.fr/dangers-de-la-route/vitesse\" target=\"_blank\">En savoir plus sur les dangers de la vitesse</a>",
            "weight": "0",
            "parent": [
                {
                    "target_id": "0"
                }
            ],
            "changed": "1529311873",
            "defaultLangcode": "1",
            "revisionTranslationAffected": "1",
            "path": [
                {
                    "langcode": "fr"
                }
            ],
            "csvValue": "Itin\u00e9raire",
            "illustration": [
                {
                    "styles": {
                        "large": {
                            "url": "/sites/default/files/styles/large/public/images/radars/itineraire.png?itok=woYb4FC_",
                            "height": "129",
                            "width": "89"
                        },
                        "medium": {
                            "url": "/sites/default/files/styles/medium/public/images/radars/itineraire.png?itok=s-IjhxwS",
                            "height": "129",
                            "width": "89"
                        },
                        "thumbnail": {
                            "url": "/sites/default/files/styles/thumbnail/public/images/radars/itineraire.png?itok=becOCQye",
                            "height": 100,
                            "width": 69
                        }
                    },
                    "infos": {
                        "fileName": "itineraire.png",
                        "fileCreated": "1519114067",
                        "fileSize": "2173",
                        "fileExtension": "png"
                    }
                }
            ],
            "macineName": "itineraire",
            "radarNameDetails": "Itin\u00e9raire"
        }
    ],
    "rulesMesured": [],
    "traceItineraire": []
}